trio_gtk.py
trio_gtk-3.0.0.dist-info/LICENSE
trio_gtk-3.0.0.dist-info/WHEEL
trio_gtk-3.0.0.dist-info/METADATA
trio_gtk-3.0.0.dist-info/RECORD
