Metadata-Version: 2.1
Name: trio-gtk
Version: 3.0.0
Summary: Trio guest mode wrapper for PyGTK
Home-page: https://github.com/decentral1se/trio-gtk
License: GPLv3
Keywords: trio,async,asyncio,curio,gtk,pygtk,gui
Author: decentral1se
Author-email: lukewm@riseup.net
Maintainer: decentral1se
Maintainer-email: lukewm@riseup.net
Requires-Python: >=3.6,<4.0
Classifier: License :: Other/Proprietary License
Classifier: Programming Language :: Python :: 3
Classifier: Programming Language :: Python :: 3.6
Classifier: Programming Language :: Python :: 3.7
Classifier: Programming Language :: Python :: 3.8
Classifier: Programming Language :: Python :: 3.9
Requires-Dist: pycairo (<1.20)
Requires-Dist: pygobject (<3.32)
Requires-Dist: trio (>=0.17.0,<0.18.0)
Project-URL: Repository, https://github.com/decentral1se/trio-gtk
